betse/__init__.py
betse/__main__.py
betse/appmeta.py
betse/exceptions.py
betse/metadata.py
betse/metadeps.py
betse/cli/__init__.py
betse/cli/__main__.py
betse/cli/cliinfo.py
betse/cli/climain.py
betse/data/yaml/sim_config.yaml
betse/data/yaml/INITS/.gitignore
betse/data/yaml/RESULTS/.gitignore
betse/data/yaml/RESULTS/init_1/.gitignore
betse/data/yaml/RESULTS/sim_1/.gitignore
betse/data/yaml/SIMS/.gitignore
betse/data/yaml/extra_configs/expression_data.yaml
betse/data/yaml/extra_configs/extra_config_template.yaml
betse/data/yaml/extra_configs/grn_basic.yaml
betse/data/yaml/extra_configs/metabo_basic.yaml
betse/data/yaml/extra_configs/metabo_test.yaml
betse/data/yaml/geo/circle/amputate.png
betse/data/yaml/geo/circle/bottom_pole.png
betse/data/yaml/geo/circle/circle_base.png
betse/data/yaml/geo/circle/circle_base_2.png
betse/data/yaml/geo/circle/mini_spot.png
betse/data/yaml/geo/circle/mini_wedge.png
betse/data/yaml/geo/circle/poles.png
betse/data/yaml/geo/circle/ring.png
betse/data/yaml/geo/circle/spot.png
betse/data/yaml/geo/circle/spot_1.png
betse/data/yaml/geo/circle/spot_2.png
betse/data/yaml/geo/circle/spot_3.png
betse/data/yaml/geo/circle/tissue_A.png
betse/data/yaml/geo/circle/tissue_B.png
betse/data/yaml/geo/circle/top_pole.png
betse/data/yaml/geo/circle/wedge.png
betse/data/yaml/geo/cyst/blastula.png
betse/data/yaml/geo/cyst/blastula2.png
betse/data/yaml/geo/cyst/ring.png
betse/data/yaml/geo/cyst/thick_side_ring.png
betse/data/yaml/geo/cyst/wedge.png
betse/data/yaml/geo/ellipse/1Hgradient.png
betse/data/yaml/geo/ellipse/1worm_1cut_high.png
betse/data/yaml/geo/ellipse/1worm_1cut_mid.png
betse/data/yaml/geo/ellipse/1worm_2cuts_asym.png
betse/data/yaml/geo/ellipse/1worm_2cuts_even.png
betse/data/yaml/geo/ellipse/1worm_5cuts.png
betse/data/yaml/geo/ellipse/1worm_base.png
betse/data/yaml/geo/ellipse/1worm_cuts.png
betse/data/yaml/geo/ellipse/1worm_cuts2.png
betse/data/yaml/geo/ellipse/1worm_head.png
betse/data/yaml/geo/ellipse/1worm_tail.png
betse-1.4.1.dist-info/METADATA
betse-1.4.1.dist-info/WHEEL
betse-1.4.1.dist-info/licenses/LICENSE
betse-1.4.1.dist-info/RECORD
