Metadata-Version: 2.3
Name: betse
Version: 1.4.1
Summary: The BioElectric Tissue Simulation Engine (BETSE) is a discrete exterior calculus simulator for 2D computational multiphysics problems in the life sciences -- including (electro)diffusion, (electro)osmosis, galvanotaxis, voltage-gated ion channels, gene regulatory networks, and biochemical reaction networks.
Project-URL: Homepage, https://calculion.streamlit.app
Project-URL: Documentation, https://www.dropbox.com/s/3rsbrjq2ljal8dl/BETSE_Documentation_April10th2019.pdf?dl=0
Project-URL: Repository, https://github.com/betsee/betse
Project-URL: Releases, https://github.com/betsee/betse/releases
Project-URL: Issues, https://github.com/betsee/betse/issues
Author-email: Alexis Pietak <alexis.pietak@gmail.com>
Maintainer-email: Cecil Curry <leycec@gmail.com>
License: Copyright 2014-2025 by Alexis Pietak & Cecil Curry.
License-File: LICENSE
Keywords: biology,multiphysics,science,simulator
Classifier: Development Status :: 5 - Production/Stable
Classifier: Intended Audience :: Science/Research
Classifier: License :: OSI Approved :: MIT License
Classifier: Natural Language :: English
Classifier: Operating System :: OS Independent
Classifier: Programming Language :: Python :: 3
Classifier: Programming Language :: Python :: 3 :: Only
Classifier: Programming Language :: Python :: 3.10
Classifier: Programming Language :: Python :: 3.11
Classifier: Programming Language :: Python :: 3.12
Classifier: Programming Language :: Python :: 3.13
Classifier: Topic :: Scientific/Engineering :: Bio-Informatics
Requires-Python: >=3.11
Requires-Dist: beartype>=0.18.0
Requires-Dist: dill>=0.2.3
Requires-Dist: matplotlib>=3.9.0
Requires-Dist: numpy>=2.0.0
Requires-Dist: pillow>=5.3.0
Requires-Dist: ruamel-yaml>=0.15.24
Requires-Dist: scipy>=1.14.0
Provides-Extra: all
Requires-Dist: coverage>=5.5; extra == 'all'
Requires-Dist: networkx>=1.2; extra == 'all'
Requires-Dist: pydot>=1.0.28; extra == 'all'
Requires-Dist: pytest>=5.4.0; extra == 'all'
Requires-Dist: sphinx; extra == 'all'
Requires-Dist: tox>=3.20.1; extra == 'all'
Provides-Extra: doc
Requires-Dist: sphinx; extra == 'doc'
Provides-Extra: test
Requires-Dist: coverage>=5.5; extra == 'test'
Requires-Dist: networkx>=1.2; extra == 'test'
Requires-Dist: pydot>=1.0.28; extra == 'test'
Requires-Dist: pytest>=5.4.0; extra == 'test'
Requires-Dist: tox>=3.20.1; extra == 'test'
Provides-Extra: test-tox
Requires-Dist: networkx>=1.2; extra == 'test-tox'
Requires-Dist: pydot>=1.0.28; extra == 'test-tox'
Requires-Dist: pytest>=5.4.0; extra == 'test-tox'
Provides-Extra: test-tox-coverage
Requires-Dist: coverage>=5.5; extra == 'test-tox-coverage'
